audeep/__init__.py
audeep/main.py
audeep/backend/__init__.py
audeep/backend/decorators.py
audeep/backend/enum_parser.py
audeep/backend/evaluation.py
audeep/backend/formatters.py
audeep/backend/learners.py
audeep/backend/log.py
audeep/backend/preprocessing.py
audeep/backend/data/__init__.py
audeep/backend/data/data_set.py
audeep/backend/data/eval_tools.py
audeep/backend/data/export.py
audeep/backend/data/import_data.py
audeep/backend/data/records.py
audeep/backend/data/upsample.py
audeep/backend/models/__init__.py
audeep/backend/models/frequency_autoencoder.py
audeep/backend/models/frequency_time_autoencoder.py
audeep/backend/models/mlp.py
audeep/backend/models/ops.py
audeep/backend/models/rnn_base.py
audeep/backend/models/spectrogram_queue.py
audeep/backend/models/summaries.py
audeep/backend/models/time_autoencoder.py
audeep/backend/parsers/__init__.py
audeep/backend/parsers/base.py
audeep/backend/parsers/compare18_atypical_affect.py
audeep/backend/parsers/compare18_crying.py
audeep/backend/parsers/compare18_heartbeat.py
audeep/backend/parsers/compare18_sas.py
audeep/backend/parsers/compare19_bs.py
audeep/backend/parsers/compare19_cs.py
audeep/backend/parsers/compare19_oa.py
audeep/backend/parsers/compare19_sd.py
audeep/backend/parsers/compare20_elderly.py
audeep/backend/parsers/compare20_mask.py
audeep/backend/parsers/cross_validated.py
audeep/backend/parsers/dcase.py
audeep/backend/parsers/dcase18_task4.py
audeep/backend/parsers/esc.py
audeep/backend/parsers/meta.py
audeep/backend/parsers/no_metadata.py
audeep/backend/parsers/partitioned.py
audeep/backend/parsers/urban_sound_8k.py
audeep/backend/signal/__init__.py
audeep/backend/signal/spectral.py
audeep/backend/training/__init__.py
audeep/backend/training/base.py
audeep/backend/training/frequency_autoencoder.py
audeep/backend/training/frequency_time_autoencoder.py
audeep/backend/training/time_autoencoder.py
audeep/cli/__init__.py
audeep/cli/evaluate.py
audeep/cli/export.py
audeep/cli/extract_spectrograms.py
auDeep-0.9.4.dist-info/LICENSE.md
auDeep-0.9.4.dist-info/METADATA
auDeep-0.9.4.dist-info/WHEEL
auDeep-0.9.4.dist-info/entry_points.txt
auDeep-0.9.4.dist-info/namespace_packages.txt
auDeep-0.9.4.dist-info/top_level.txt
auDeep-0.9.4.dist-info/RECORD
