Metadata-Version: 2.1
Name: auDeep
Version: 0.9.4
Summary: auDeep is a Python toolkit for unsupervised feature learning with deep neural networks (DNNs)
Home-page: https://github.com/auDeep/auDeep
Author: Maurice Gerczuk
Author-email: maurice.gerczuk@informatik.uni-augsburg.de
License: GPLv3+
Project-URL: Source, https://github.com/auDeep/auDeep/
Project-URL: Tracker, https://github.com/auDeep/auDeep/issues
Keywords: machine-learning audio-analysis science research
Platform: Any
Classifier: Development Status :: 4 - Beta
Classifier: Environment :: GPU :: NVIDIA CUDA :: 10.0
Classifier: Topic :: Scientific/Engineering :: Artificial Intelligence
Classifier: Intended Audience :: Science/Research
Classifier: License :: OSI Approved :: GNU General Public License v3 (GPLv3)
Classifier: Programming Language :: Python :: 3.7
Requires-Dist: cliff (>=3.3)
Requires-Dist: liac-arff (>=2.4)
Requires-Dist: matplotlib (>=3.2)
Requires-Dist: netCDF4 (==1.4.2)
Requires-Dist: pandas (>=1.0)
Requires-Dist: pysoundfile (>=0.9)
Requires-Dist: scipy (>=1.4)
Requires-Dist: scikit-learn (>=0.23)
Requires-Dist: xarray (==0.10.0)
Requires-Dist: tensorflow-gpu (<2,>=1.15.2)
